bumpers/__init__.py
bumpers/analytics/__init__.py
bumpers/analytics/analyzer.py
bumpers/core/__init__.py
bumpers/core/engine.py
bumpers/integrations/__init__.py
bumpers/integrations/langchain_callback.py
bumpers/integrations/react.py
bumpers/logging/__init__.py
bumpers/logging/base.py
bumpers/logging/file_logger.py
bumpers/monitoring/__init__.py
bumpers/monitoring/conditions.py
bumpers/monitoring/monitor.py
bumpers/policy/__init__.py
bumpers/policy/parser.py
bumpers/validators/__init__.py
bumpers/validators/action.py
bumpers/validators/base.py
bumpers/validators/chain_length.py
bumpers/validators/content.py
bumpers/validators/goal_fulfillment.py
bumpers/validators/llm_safety.py
bumpers/validators/pattern.py
bumpers/validators/rate_limit.py
bumpers/validators/redundancy_looping.py
bumpers/validators/resource.py
bumpers/validators/semantic.py
bumpers/validators/temporal_relevance.py
bumpers-0.1.1.dist-info/METADATA
bumpers-0.1.1.dist-info/WHEEL
bumpers-0.1.1.dist-info/top_level.txt
bumpers-0.1.1.dist-info/RECORD
