Metadata-Version: 2.1
Name: bumpers
Version: 0.1.1
Summary: Safety/alignment guardrails for AI agents
Home-page: https://github.com/pythonomar22/bumpers
Author: Omar Abul-Hassan
Author-email: omarah@stanford.edu
Classifier: Development Status :: 3 - Alpha
Classifier: Intended Audience :: Developers
Classifier: License :: OSI Approved :: MIT License
Classifier: Programming Language :: Python :: 3
Classifier: Programming Language :: Python :: 3.8
Classifier: Programming Language :: Python :: 3.9
Classifier: Programming Language :: Python :: 3.10
Requires-Python: >=3.8
Requires-Dist: numpy
Requires-Dist: pyyaml
Requires-Dist: httpx
Requires-Dist: langchain
Requires-Dist: sentence-transformers
Requires-Dist: cerebras-cloud-sdk
Requires-Dist: torch
Requires-Dist: openai>=1.0.0
Provides-Extra: dev
Requires-Dist: pytest; extra == "dev"
Requires-Dist: black; extra == "dev"
Requires-Dist: flake8; extra == "dev"
